eazure/__init__.py
eazure/blob.py
eazure/queue.py
eazure/table.py
eazure-0.1.2.dist-info/LICENSE
eazure-0.1.2.dist-info/WHEEL
eazure-0.1.2.dist-info/METADATA
eazure-0.1.2.dist-info/RECORD
