Metadata-Version: 2.1
Name: eazure
Version: 0.1.2
Summary: Eazure: A package providing easier access to Azure storage, tables, and queue functions.
Author-email: SaaS Technologies LLC <newsaastechnologies@gmail.com>
Requires-Python: >=3.7
Requires-Dist: azure-storage-blob >=12.8.1
Requires-Dist: azure-core >=1.9.0
Requires-Dist: azure-data-tables >=12.0.0
Requires-Dist: azure-storage-queue >=12.1.5
Requires-Dist: tox ; extra == "dev"
Requires-Dist: pre-commit ; extra == "dev"
Requires-Dist: bump2version ; extra == "dev"
Project-URL: Bug Reports, https://github.com/SaaS-Technologies-LLC/eazure/issues
Project-URL: Homepage, https://github.com/SaaS-Technologies-LLC/eazure
Project-URL: Source, https://github.com/SaaS-Technologies-LLC/eazure/
Provides-Extra: dev
